{
  "db_name": "PostgreSQL",
  "query": "\n            SELECT person.*\n            FROM person\n                JOIN user_catalog ON user_catalog.catalog=person.catalog\n            WHERE\n                user_catalog.user=$1\n            ",
  "describe": {
    "columns": [
      {
        "ordinal": 0,
        "name": "id",
        "type_info": "Varchar"
      },
      {
        "ordinal": 1,
        "name": "name",
        "type_info": "Text"
      },
      {
        "ordinal": 2,
        "name": "catalog",
        "type_info": "Varchar"
      }
    ],
    "parameters": {
      "Left": [
        "Text"
      ]
    },
    "nullable": [
      false,
      false,
      false
    ]
  },
  "hash": "7040e6a2cc74f1fe3d8bdbcfb979e0a02630a1e5ee657b7eee76959e5cf1275f"
}
